api_request_operations_ivy/__init__.py
api_request_operations_ivy/api_request.py
api_request_operations_ivy-0.1.0.dist-info/METADATA
api_request_operations_ivy-0.1.0.dist-info/WHEEL
api_request_operations_ivy-0.1.0.dist-info/RECORD
