Metadata-Version: 2.1
Name: api-request-operations-ivy
Version: 0.1.0
Summary: 
Author: Patrick White
Author-email: whitep@vcu.edu
Requires-Python: >=3.11,<4.0
Classifier: Programming Language :: Python :: 3
Classifier: Programming Language :: Python :: 3.11
Requires-Dist: pre-commit (>=4.2.0,<5.0.0)
Requires-Dist: pytest (>=8.3.5,<9.0.0)
Requires-Dist: requests (>=2.32.3,<3.0.0)
